prediction.py
cis_bcw-0.1.0.dist-info/METADATA
cis_bcw-0.1.0.dist-info/WHEEL
cis_bcw-0.1.0.dist-info/RECORD
