Metadata-Version: 2.1
Name: CIS_BCW
Version: 0.1.0
Summary: 
Author: CIS
Requires-Python: >=3.8,<3.10
Classifier: Programming Language :: Python :: 3
Classifier: Programming Language :: Python :: 3.8
Classifier: Programming Language :: Python :: 3.9
Requires-Dist: pandas (<3.0.0)
